{"info":{"name":"Burek","tempo":"55"},"preload":["A2-m7 [w]","D2-7 [w]","G2-maj7 [w]","C2-maj7 [w]","F#2-m7 [t]","B1-7 [w]","E2-m"],"noteDurations":{"whole":"4.4","half":"2.2","quarter":"1.1","eigth":"0.6","sixteenth":"0.3"},"sections":[{"name":"theme","iterations":"4","chords":[{"name":"A2-m7 [w]","root":"A2","type":"m7 [w]","multiplier":"1","duration":"half","time_duration":"2.2","checkpoint":"true","checkpoint_offset_multiplier":"1","checkpoint_offset_value":"quarter","checkpoint_offset_time":"1.1","checkpoint_duration_multiplier":"1","checkpoint_duration_value":"quarter","checkpoint_duration_time":"1.1"},{"name":"D2-7 [w]","root":"D2","type":"7 [w]","multiplier":"1","duration":"half","time_duration":"2.2","checkpoint":"true","checkpoint_offset_multiplier":"1","checkpoint_offset_value":"quarter","checkpoint_offset_time":"1.1","checkpoint_duration_multiplier":"1","checkpoint_duration_value":"quarter","checkpoint_duration_time":"1.1"},{"name":"G2-maj7 [w]","root":"G2","type":"maj7 [w]","multiplier":"1","duration":"half","time_duration":"2.2","checkpoint":"true","checkpoint_offset_multiplier":"1","checkpoint_offset_value":"quarter","checkpoint_offset_time":"1.1","checkpoint_duration_multiplier":"1","checkpoint_duration_value":"quarter","checkpoint_duration_time":"1.1"},{"name":"C2-maj7 [w]","root":"C2","type":"maj7 [w]","multiplier":"1","duration":"half","time_duration":"2.2","checkpoint":"true","checkpoint_offset_multiplier":"1","checkpoint_offset_value":"quarter","checkpoint_offset_time":"1.1","checkpoint_duration_multiplier":"1","checkpoint_duration_value":"quarter","checkpoint_duration_time":"1.1"},{"name":"F#2-m7 [t]","root":"F#2","type":"m7 [t]","multiplier":"1","duration":"half","time_duration":"2.2","checkpoint":"true","checkpoint_offset_multiplier":"1","checkpoint_offset_value":"quarter","checkpoint_offset_time":"1.1","checkpoint_duration_multiplier":"1","checkpoint_duration_value":"quarter","checkpoint_duration_time":"1.1"},{"name":"B1-7 [w]","root":"B1","type":"7 [w]","multiplier":"1","duration":"half","time_duration":"2.2","checkpoint":"true","checkpoint_offset_multiplier":"1","checkpoint_offset_value":"quarter","checkpoint_offset_time":"1.1","checkpoint_duration_multiplier":"1","checkpoint_duration_value":"quarter","checkpoint_duration_time":"1.1"},{"name":"E2-m","root":"E2","type":"m","multiplier":"1","duration":"half","time_duration":"2.2","checkpoint":"false","checkpoint_offset_multiplier":"1","checkpoint_offset_value":"quarter","checkpoint_offset_time":"1.1","checkpoint_duration_multiplier":"1","checkpoint_duration_value":"quarter","checkpoint_duration_time":"1.1"},{"name":"E2-m","root":"E2","type":"m","multiplier":"1","duration":"half","time_duration":"2.2","checkpoint":"false","checkpoint_offset_multiplier":"1","checkpoint_offset_value":"quarter","checkpoint_offset_time":"1.1","checkpoint_duration_multiplier":"1","checkpoint_duration_value":"quarter","checkpoint_duration_time":"1.1"}]}]}